MANIFEST.in
README.rst
setup.cfg
setup.py
zpm
zpm.egg-info/PKG-INFO
zpm.egg-info/SOURCES.txt
zpm.egg-info/dependency_links.txt
zpm.egg-info/requires.txt
zpm.egg-info/top_level.txt
zpmlib/__init__.py
zpmlib/commands.py
zpmlib/zpm.py
zpmlib/templates/index.html.tmpl
zpmlib/templates/style.css
zpmlib/templates/zapp-with-ui.yaml
zpmlib/templates/zapp.yaml
zpmlib/templates/zerocloud.js