Metadata-Version: 1.1
Name: zpm
Version: 0.3
Summary: ZeroVM Package Manager
Home-page: https://github.com/zerovm/zpm
Author: ZeroVM Team
Author-email: zerovm@rackspace.com
License: Apache 2.0
Keywords: zpm zerovm zvm
Platform: any
Classifier: Development Status :: 3 - Alpha
Classifier: License :: OSI Approved :: Apache Software License
Classifier: Intended Audience :: Developers
Classifier: Intended Audience :: Information Technology
Classifier: Operating System :: OS Independent
Classifier: Programming Language :: Python :: 2
Classifier: Programming Language :: Python :: 2.6
Classifier: Programming Language :: Python :: 2.7
Classifier: Programming Language :: Python :: 3
Classifier: Programming Language :: Python :: 3.3
Classifier: Programming Language :: Python :: 3.4
Classifier: Topic :: Software Development :: Build Tools
Provides: zpm (0.3)
